LICENSE
README.md
setup.py
KanNet.egg-info/PKG-INFO
KanNet.egg-info/SOURCES.txt
KanNet.egg-info/dependency_links.txt
KanNet.egg-info/requires.txt
KanNet.egg-info/top_level.txt
kannet/__init__.py
kannet/models.py