Metadata-Version: 2.1
Name: KanNet
Version: 0.0.1
Summary: my amazing package
Home-page: https://github.com/xuehangcang/KanNet
Author: XuehangCang
Author-email: XuehangCang@outlook.com
Keywords: kan,pykan,Kolmogorov-Arnold Networks (KANs)
Classifier: Development Status :: 1 - Planning
Classifier: Intended Audience :: Developers
Classifier: Programming Language :: Python :: 3
Classifier: Operating System :: Unix
Classifier: Operating System :: MacOS :: MacOS X
Classifier: Operating System :: Microsoft :: Windows
License-File: LICENSE
Requires-Dist: torch~=2.3.0
Requires-Dist: torchvision~=0.18.0
Requires-Dist: tqdm~=4.66.4
